{
  "dialect": "postgres",
  "id": "e09b3d66-f091-43bc-b072-fac216bf8799",
  "prevIds": ["385d476b-d4f6-48a3-99e6-0a95af4ee4e4"],
  "version": "8",
  "ddl": [
    {
      "isRlsEnabled": false,
      "name": "relay_dpop_proofs",
      "entityType": "tables",
      "schema": "public"
    },
    {
      "isRlsEnabled": false,
      "name": "relay_environment_credentials",
      "entityType": "tables",
      "schema": "public"
    },
    {
      "isRlsEnabled": false,
      "name": "relay_environment_links",
      "entityType": "tables",
      "schema": "public"
    },
    {
      "isRlsEnabled": false,
      "name": "relay_environment_operations",
      "entityType": "tables",
      "schema": "public"
    },
    {
      "isRlsEnabled": false,
      "name": "relay_managed_endpoint_allocations",
      "entityType": "tables",
      "schema": "public"
    },
    {
      "type": "varchar(128)",
      "typeSchema": null,
      "notNull": true,
      "dimensions": 0,
      "default": null,
      "generated": null,
      "identity": null,
      "name": "thumbprint",
      "entityType": "columns",
      "schema": "public",
      "table": "relay_dpop_proofs"
    },
    {
      "type": "varchar(255)",
      "typeSchema": null,
      "notNull": true,
      "dimensions": 0,
      "default": null,
      "generated": null,
      "identity": null,
      "name": "jti",
      "entityType": "columns",
      "schema": "public",
      "table": "relay_dpop_proofs"
    },
    {
      "type": "integer",
      "typeSchema": null,
      "notNull": true,
      "dimensions": 0,
      "default": null,
      "generated": null,
      "identity": null,
      "name": "iat",
      "entityType": "columns",
      "schema": "public",
      "table": "relay_dpop_proofs"
    },
    {
      "type": "varchar(64)",
      "typeSchema": null,
      "notNull": true,
      "dimensions": 0,
      "default": null,
      "generated": null,
      "identity": null,
      "name": "expires_at",
      "entityType": "columns",
      "schema": "public",
      "table": "relay_dpop_proofs"
    },
    {
      "type": "varchar(64)",
      "typeSchema": null,
      "notNull": true,
      "dimensions": 0,
      "default": null,
      "generated": null,
      "identity": null,
      "name": "created_at",
      "entityType": "columns",
      "schema": "public",
      "table": "relay_dpop_proofs"
    },
    {
      "type": "varchar(64)",
      "typeSchema": null,
      "notNull": true,
      "dimensions": 0,
      "default": null,
      "generated": null,
      "identity": null,
      "name": "credential_id",
      "entityType": "columns",
      "schema": "public",
      "table": "relay_environment_credentials"
    },
    {
      "type": "varchar(191)",
      "typeSchema": null,
      "notNull": true,
      "dimensions": 0,
      "default": null,
      "generated": null,
      "identity": null,
      "name": "environment_id",
      "entityType": "columns",
      "schema": "public",
      "table": "relay_environment_credentials"
    },
    {
      "type": "text",
      "typeSchema": null,
      "notNull": true,
      "dimensions": 0,
      "default": null,
      "generated": null,
      "identity": null,
      "name": "environment_public_key",
      "entityType": "columns",
      "schema": "public",
      "table": "relay_environment_credentials"
    },
    {
      "type": "varchar(191)",
      "typeSchema": null,
      "notNull": true,
      "dimensions": 0,
      "default": null,
      "generated": null,
      "identity": null,
      "name": "credential_hash",
      "entityType": "columns",
      "schema": "public",
      "table": "relay_environment_credentials"
    },
    {
      "type": "varchar(64)",
      "typeSchema": null,
      "notNull": false,
      "dimensions": 0,
      "default": null,
      "generated": null,
      "identity": null,
      "name": "revoked_at",
      "entityType": "columns",
      "schema": "public",
      "table": "relay_environment_credentials"
    },
    {
      "type": "varchar(64)",
      "typeSchema": null,
      "notNull": true,
      "dimensions": 0,
      "default": null,
      "generated": null,
      "identity": null,
      "name": "created_at",
      "entityType": "columns",
      "schema": "public",
      "table": "relay_environment_credentials"
    },
    {
      "type": "varchar(64)",
      "typeSchema": null,
      "notNull": true,
      "dimensions": 0,
      "default": null,
      "generated": null,
      "identity": null,
      "name": "updated_at",
      "entityType": "columns",
      "schema": "public",
      "table": "relay_environment_credentials"
    },
    {
      "type": "varchar(191)",
      "typeSchema": null,
      "notNull": true,
      "dimensions": 0,
      "default": null,
      "generated": null,
      "identity": null,
      "name": "user_id",
      "entityType": "columns",
      "schema": "public",
      "table": "relay_environment_links"
    },
    {
      "type": "varchar(191)",
      "typeSchema": null,
      "notNull": true,
      "dimensions": 0,
      "default": null,
      "generated": null,
      "identity": null,
      "name": "environment_id",
      "entityType": "columns",
      "schema": "public",
      "table": "relay_environment_links"
    },
    {
      "type": "text",
      "typeSchema": null,
      "notNull": true,
      "dimensions": 0,
      "default": "'T4 Environment'",
      "generated": null,
      "identity": null,
      "name": "environment_label",
      "entityType": "columns",
      "schema": "public",
      "table": "relay_environment_links"
    },
    {
      "type": "text",
      "typeSchema": null,
      "notNull": true,
      "dimensions": 0,
      "default": null,
      "generated": null,
      "identity": null,
      "name": "environment_public_key",
      "entityType": "columns",
      "schema": "public",
      "table": "relay_environment_links"
    },
    {
      "type": "text",
      "typeSchema": null,
      "notNull": true,
      "dimensions": 0,
      "default": null,
      "generated": null,
      "identity": null,
      "name": "endpoint_http_base_url",
      "entityType": "columns",
      "schema": "public",
      "table": "relay_environment_links"
    },
    {
      "type": "text",
      "typeSchema": null,
      "notNull": true,
      "dimensions": 0,
      "default": null,
      "generated": null,
      "identity": null,
      "name": "endpoint_ws_base_url",
      "entityType": "columns",
      "schema": "public",
      "table": "relay_environment_links"
    },
    {
      "type": "varchar(32)",
      "typeSchema": null,
      "notNull": true,
      "dimensions": 0,
      "default": null,
      "generated": null,
      "identity": null,
      "name": "endpoint_provider_kind",
      "entityType": "columns",
      "schema": "public",
      "table": "relay_environment_links"
    },
    {
      "type": "boolean",
      "typeSchema": null,
      "notNull": true,
      "dimensions": 0,
      "default": "false",
      "generated": null,
      "identity": null,
      "name": "managed_tunnels_enabled",
      "entityType": "columns",
      "schema": "public",
      "table": "relay_environment_links"
    },
    {
      "type": "varchar(64)",
      "typeSchema": null,
      "notNull": false,
      "dimensions": 0,
      "default": null,
      "generated": null,
      "identity": null,
      "name": "revoked_at",
      "entityType": "columns",
      "schema": "public",
      "table": "relay_environment_links"
    },
    {
      "type": "varchar(64)",
      "typeSchema": null,
      "notNull": true,
      "dimensions": 0,
      "default": null,
      "generated": null,
      "identity": null,
      "name": "created_at",
      "entityType": "columns",
      "schema": "public",
      "table": "relay_environment_links"
    },
    {
      "type": "varchar(64)",
      "typeSchema": null,
      "notNull": true,
      "dimensions": 0,
      "default": null,
      "generated": null,
      "identity": null,
      "name": "updated_at",
      "entityType": "columns",
      "schema": "public",
      "table": "relay_environment_links"
    },
    {
      "type": "varchar(191)",
      "typeSchema": null,
      "notNull": true,
      "dimensions": 0,
      "default": null,
      "generated": null,
      "identity": null,
      "name": "environment_id",
      "entityType": "columns",
      "schema": "public",
      "table": "relay_environment_operations"
    },
    {
      "type": "integer",
      "typeSchema": null,
      "notNull": true,
      "dimensions": 0,
      "default": "0",
      "generated": null,
      "identity": null,
      "name": "generation",
      "entityType": "columns",
      "schema": "public",
      "table": "relay_environment_operations"
    },
    {
      "type": "varchar(64)",
      "typeSchema": null,
      "notNull": false,
      "dimensions": 0,
      "default": null,
      "generated": null,
      "identity": null,
      "name": "owner_token",
      "entityType": "columns",
      "schema": "public",
      "table": "relay_environment_operations"
    },
    {
      "type": "varchar(191)",
      "typeSchema": null,
      "notNull": false,
      "dimensions": 0,
      "default": null,
      "generated": null,
      "identity": null,
      "name": "owner_user_id",
      "entityType": "columns",
      "schema": "public",
      "table": "relay_environment_operations"
    },
    {
      "type": "varchar(32)",
      "typeSchema": null,
      "notNull": false,
      "dimensions": 0,
      "default": null,
      "generated": null,
      "identity": null,
      "name": "operation_kind",
      "entityType": "columns",
      "schema": "public",
      "table": "relay_environment_operations"
    },
    {
      "type": "varchar(64)",
      "typeSchema": null,
      "notNull": false,
      "dimensions": 0,
      "default": null,
      "generated": null,
      "identity": null,
      "name": "lease_expires_at",
      "entityType": "columns",
      "schema": "public",
      "table": "relay_environment_operations"
    },
    {
      "type": "varchar(64)",
      "typeSchema": null,
      "notNull": true,
      "dimensions": 0,
      "default": null,
      "generated": null,
      "identity": null,
      "name": "created_at",
      "entityType": "columns",
      "schema": "public",
      "table": "relay_environment_operations"
    },
    {
      "type": "varchar(64)",
      "typeSchema": null,
      "notNull": true,
      "dimensions": 0,
      "default": null,
      "generated": null,
      "identity": null,
      "name": "updated_at",
      "entityType": "columns",
      "schema": "public",
      "table": "relay_environment_operations"
    },
    {
      "type": "varchar(191)",
      "typeSchema": null,
      "notNull": true,
      "dimensions": 0,
      "default": null,
      "generated": null,
      "identity": null,
      "name": "user_id",
      "entityType": "columns",
      "schema": "public",
      "table": "relay_managed_endpoint_allocations"
    },
    {
      "type": "varchar(191)",
      "typeSchema": null,
      "notNull": true,
      "dimensions": 0,
      "default": null,
      "generated": null,
      "identity": null,
      "name": "environment_id",
      "entityType": "columns",
      "schema": "public",
      "table": "relay_managed_endpoint_allocations"
    },
    {
      "type": "text",
      "typeSchema": null,
      "notNull": true,
      "dimensions": 0,
      "default": null,
      "generated": null,
      "identity": null,
      "name": "hostname",
      "entityType": "columns",
      "schema": "public",
      "table": "relay_managed_endpoint_allocations"
    },
    {
      "type": "varchar(191)",
      "typeSchema": null,
      "notNull": false,
      "dimensions": 0,
      "default": null,
      "generated": null,
      "identity": null,
      "name": "tunnel_id",
      "entityType": "columns",
      "schema": "public",
      "table": "relay_managed_endpoint_allocations"
    },
    {
      "type": "text",
      "typeSchema": null,
      "notNull": true,
      "dimensions": 0,
      "default": null,
      "generated": null,
      "identity": null,
      "name": "tunnel_name",
      "entityType": "columns",
      "schema": "public",
      "table": "relay_managed_endpoint_allocations"
    },
    {
      "type": "varchar(191)",
      "typeSchema": null,
      "notNull": false,
      "dimensions": 0,
      "default": null,
      "generated": null,
      "identity": null,
      "name": "dns_record_id",
      "entityType": "columns",
      "schema": "public",
      "table": "relay_managed_endpoint_allocations"
    },
    {
      "type": "varchar(64)",
      "typeSchema": null,
      "notNull": false,
      "dimensions": 0,
      "default": null,
      "generated": null,
      "identity": null,
      "name": "ready_at",
      "entityType": "columns",
      "schema": "public",
      "table": "relay_managed_endpoint_allocations"
    },
    {
      "type": "integer",
      "typeSchema": null,
      "notNull": true,
      "dimensions": 0,
      "default": "0",
      "generated": null,
      "identity": null,
      "name": "operation_generation",
      "entityType": "columns",
      "schema": "public",
      "table": "relay_managed_endpoint_allocations"
    },
    {
      "type": "varchar(64)",
      "typeSchema": null,
      "notNull": false,
      "dimensions": 0,
      "default": null,
      "generated": null,
      "identity": null,
      "name": "operation_owner_token",
      "entityType": "columns",
      "schema": "public",
      "table": "relay_managed_endpoint_allocations"
    },
    {
      "type": "varchar(64)",
      "typeSchema": null,
      "notNull": true,
      "dimensions": 0,
      "default": null,
      "generated": null,
      "identity": null,
      "name": "created_at",
      "entityType": "columns",
      "schema": "public",
      "table": "relay_managed_endpoint_allocations"
    },
    {
      "type": "varchar(64)",
      "typeSchema": null,
      "notNull": true,
      "dimensions": 0,
      "default": null,
      "generated": null,
      "identity": null,
      "name": "updated_at",
      "entityType": "columns",
      "schema": "public",
      "table": "relay_managed_endpoint_allocations"
    },
    {
      "nameExplicit": true,
      "columns": [
        {
          "value": "expires_at",
          "isExpression": false,
          "asc": true,
          "nullsFirst": false,
          "opclass": null
        }
      ],
      "isUnique": false,
      "where": null,
      "with": "",
      "method": "btree",
      "concurrently": false,
      "name": "idx_relay_dpop_proofs_expires_at",
      "entityType": "indexes",
      "schema": "public",
      "table": "relay_dpop_proofs"
    },
    {
      "nameExplicit": true,
      "columns": [
        {
          "value": "credential_hash",
          "isExpression": false,
          "asc": true,
          "nullsFirst": false,
          "opclass": null
        }
      ],
      "isUnique": true,
      "where": null,
      "with": "",
      "method": "btree",
      "concurrently": false,
      "name": "idx_relay_environment_credentials_hash",
      "entityType": "indexes",
      "schema": "public",
      "table": "relay_environment_credentials"
    },
    {
      "nameExplicit": true,
      "columns": [
        {
          "value": "environment_id",
          "isExpression": false,
          "asc": true,
          "nullsFirst": false,
          "opclass": null
        },
        {
          "value": "revoked_at",
          "isExpression": false,
          "asc": true,
          "nullsFirst": false,
          "opclass": null
        }
      ],
      "isUnique": false,
      "where": null,
      "with": "",
      "method": "btree",
      "concurrently": false,
      "name": "idx_relay_environment_credentials_environment",
      "entityType": "indexes",
      "schema": "public",
      "table": "relay_environment_credentials"
    },
    {
      "nameExplicit": true,
      "columns": [
        {
          "value": "environment_id",
          "isExpression": false,
          "asc": true,
          "nullsFirst": false,
          "opclass": null
        },
        {
          "value": "environment_public_key",
          "isExpression": false,
          "asc": true,
          "nullsFirst": false,
          "opclass": null
        },
        {
          "value": "revoked_at",
          "isExpression": false,
          "asc": true,
          "nullsFirst": false,
          "opclass": null
        }
      ],
      "isUnique": false,
      "where": null,
      "with": "",
      "method": "btree",
      "concurrently": false,
      "name": "idx_relay_environment_credentials_environment_key",
      "entityType": "indexes",
      "schema": "public",
      "table": "relay_environment_credentials"
    },
    {
      "nameExplicit": true,
      "columns": [
        {
          "value": "environment_id",
          "isExpression": false,
          "asc": true,
          "nullsFirst": false,
          "opclass": null
        },
        {
          "value": "environment_public_key",
          "isExpression": false,
          "asc": true,
          "nullsFirst": false,
          "opclass": null
        }
      ],
      "isUnique": true,
      "where": "\"revoked_at\" is null",
      "with": "",
      "method": "btree",
      "concurrently": false,
      "name": "idx_relay_environment_credentials_active_environment_key",
      "entityType": "indexes",
      "schema": "public",
      "table": "relay_environment_credentials"
    },
    {
      "nameExplicit": true,
      "columns": [
        {
          "value": "environment_id",
          "isExpression": false,
          "asc": true,
          "nullsFirst": false,
          "opclass": null
        },
        {
          "value": "revoked_at",
          "isExpression": false,
          "asc": true,
          "nullsFirst": false,
          "opclass": null
        }
      ],
      "isUnique": false,
      "where": null,
      "with": "",
      "method": "btree",
      "concurrently": false,
      "name": "idx_relay_environment_links_environment",
      "entityType": "indexes",
      "schema": "public",
      "table": "relay_environment_links"
    },
    {
      "nameExplicit": true,
      "columns": [
        {
          "value": "lease_expires_at",
          "isExpression": false,
          "asc": true,
          "nullsFirst": false,
          "opclass": null
        }
      ],
      "isUnique": false,
      "where": null,
      "with": "",
      "method": "btree",
      "concurrently": false,
      "name": "idx_relay_environment_operations_lease",
      "entityType": "indexes",
      "schema": "public",
      "table": "relay_environment_operations"
    },
    {
      "nameExplicit": true,
      "columns": [
        {
          "value": "hostname",
          "isExpression": false,
          "asc": true,
          "nullsFirst": false,
          "opclass": null
        }
      ],
      "isUnique": true,
      "where": null,
      "with": "",
      "method": "btree",
      "concurrently": false,
      "name": "idx_relay_managed_endpoint_allocations_hostname",
      "entityType": "indexes",
      "schema": "public",
      "table": "relay_managed_endpoint_allocations"
    },
    {
      "nameExplicit": true,
      "columns": [
        {
          "value": "tunnel_name",
          "isExpression": false,
          "asc": true,
          "nullsFirst": false,
          "opclass": null
        }
      ],
      "isUnique": true,
      "where": null,
      "with": "",
      "method": "btree",
      "concurrently": false,
      "name": "idx_relay_managed_endpoint_allocations_tunnel_name",
      "entityType": "indexes",
      "schema": "public",
      "table": "relay_managed_endpoint_allocations"
    },
    {
      "columns": ["thumbprint", "jti"],
      "nameExplicit": false,
      "name": "relay_dpop_proofs_pkey",
      "entityType": "pks",
      "schema": "public",
      "table": "relay_dpop_proofs"
    },
    {
      "columns": ["user_id", "environment_id"],
      "nameExplicit": false,
      "name": "relay_environment_links_pkey",
      "entityType": "pks",
      "schema": "public",
      "table": "relay_environment_links"
    },
    {
      "columns": ["environment_id"],
      "nameExplicit": false,
      "name": "relay_environment_operations_pkey",
      "entityType": "pks",
      "schema": "public",
      "table": "relay_environment_operations"
    },
    {
      "columns": ["user_id", "environment_id"],
      "nameExplicit": false,
      "name": "relay_managed_endpoint_allocations_pkey",
      "entityType": "pks",
      "schema": "public",
      "table": "relay_managed_endpoint_allocations"
    },
    {
      "columns": ["credential_id"],
      "nameExplicit": false,
      "name": "relay_environment_credentials_pkey",
      "schema": "public",
      "table": "relay_environment_credentials",
      "entityType": "pks"
    }
  ],
  "renames": []
}
